langchain_lindorm_integration/__init__.py
langchain_lindorm_integration/byte_store.py
langchain_lindorm_integration/embeddings.py
langchain_lindorm_integration/helper/__init__.py
langchain_lindorm_integration/helper/vectorstore.py
langchain_lindorm_integration/py.typed
langchain_lindorm_integration/reranker.py
langchain_lindorm_integration/vectorstores.py
langchain_lindorm_integration-0.1.1.dist-info/LICENSE
langchain_lindorm_integration-0.1.1.dist-info/METADATA
langchain_lindorm_integration-0.1.1.dist-info/WHEEL
langchain_lindorm_integration-0.1.1.dist-info/RECORD
